CHANGELOG.txt
LICENCE.txt
MANIFEST.in
README.txt
setup.py
tahirovisu/__init__.py
tahirovisu.egg-info/PKG-INFO
tahirovisu.egg-info/SOURCES.txt
tahirovisu.egg-info/dependency_links.txt
tahirovisu.egg-info/top_level.txt