Metadata-Version: 2.1
Name: tahirovisu
Version: 0.0.1
Summary: A very basic Python package demo
Home-page: UNKNOWN
Author: Tahir MAT
Author-email: matahir33@gmail.com
License: MIT
Keywords: visualization
Platform: UNKNOWN
Classifier: Development Status :: 5 - Production/Stable
Classifier: Intended Audience :: Education
Classifier: Operating System :: Microsoft :: Windows :: Windows 10
Classifier: License :: OSI Approved :: MIT License
Classifier: Programming Language :: Python :: 3
License-File: LICENCE.txt
